tv002/__init__.py
tv002-0.0.1.dist-info/METADATA
tv002-0.0.1.dist-info/WHEEL
tv002-0.0.1.dist-info/top_level.txt
tv002-0.0.1.dist-info/RECORD
