Metadata-Version: 2.1
Name: tv002
Version: 0.0.1
Summary: This is the simplest module for quick work with files.
Author: fertic
Author-email: foxmine852@gmail.com
Keywords: files speedfiles
Classifier: Programming Language :: Python :: 3.11
Classifier: License :: OSI Approved :: MIT License
Classifier: Operating System :: OS Independent
Requires-Dist: requests >=2.25.1
